{
  "$schema": "https://developer.microsoft.com/json-schemas/fabric/item/report/definition/visualContainer/2.4.0/schema.json",
  "name": "3d8a2353790c81313d7b",
  "position": {
    "x": 776.25,
    "y": 97.5,
    "z": 3000,
    "height": 31.25,
    "width": 178.75,
    "tabOrder": 3000
  },
  "visual": {
    "visualType": "card",
    "query": {
      "queryState": {
        "Values": {
          "projections": [
            {
              "field": {
                "Measure": {
                  "Expression": {
                    "SourceRef": {
                      "Entity": "2 Mesure technical monitoring"
                    }
                  },
                  "Property": "Average response time (controller)"
                }
              },
              "queryRef": "0 Mesure technical monitoring.Average response time (controller)",
              "nativeQueryRef": "Average response time (controller)"
            }
          ]
        }
      },
      "sortDefinition": {
        "sort": [
          {
            "field": {
              "Measure": {
                "Expression": {
                  "SourceRef": {
                    "Entity": "2 Mesure technical monitoring"
                  }
                },
                "Property": "Average response time (controller)"
              }
            },
            "direction": "Descending"
          }
        ],
        "isDefaultSort": true
      }
    },
    "objects": {
      "labels": [
        {
          "properties": {
            "fontSize": {
              "expr": {
                "Literal": {
                  "Value": "14D"
                }
              }
            }
          }
        }
      ],
      "categoryLabels": [
        {
          "properties": {
            "show": {
              "expr": {
                "Literal": {
                  "Value": "false"
                }
              }
            }
          }
        }
      ]
    },
    "drillFilterOtherVisuals": true
  }
}